Workbook

Sheet Summary
B2: D01
B3: RAK Doors · Ras Al Khaimah
B6: 1 | C6: PROJECT INFORMATION
B7: Project | C7: RAK Doors
B8: Location | C8: Ras Al Khaimah
B9: Type | C9: D01
B10: Date | C10: 2026-10-13
B11: Revision | C11: B
B12: Currency / VAT | C12: AED (VAT 5%)
B13: Main contractor | C13: Example Contracting LLC
B14: Design consultant | C14: Example Design Studio
B15: Supervision | C15: —
B17: 2 | C17: DRAWINGS | E17: 2 sheets
B18: Ref 01 | C18: ARAK-P1R1-INB-SD-ID-RES-ZZZ-3320277-02.pdf
B19: Ref 02 | C19: ARAK-P1R1-INB-SD-ID-RES-ZZZ-3320361-01.pdf
B21: 3 | C21: BILL SUMMARY BY SECTION
B22: Section | C22: Description | D22: Items | F22: Amount
B23: H | C23: Doors and windows | D23: 5 | F23: ='Bill of Quantities'!G14
C24: Total of the bill | F24: =SUM(F23:F23)
B26: 4 | C26: ESTIMATE · MEASURED WORK TO TENDER SUM
C27: Note | E27: % | F27: Amount
B28: Measured work | C28: Quantity × rate, from the takeoff | F28: ='Takeoff'!K25 -> 1556.03
B29: Preliminaries | C29: Site setup, supervision, temporary works, insurances | E29: 0.05 | F29: =F28*E29 -> 77.8
B30: Provisional sums | C30: Allowances for work not yet designed | F30: 0
B31: Works cost | F31: =F28+F29+F30 -> 1633.84
B32: Contingency | C32: Risk allowance, on the works cost | E32: 0.03 | F32: =F31*E32 -> 49.02
B33: Overheads | C33: Head-office cost | E33: 0.07 | F33: =(F31+F32)*E33 -> 117.8
B34: Profit | E34: 0.1 | F34: =(F31+F32+F33)*E34 -> 180.07
B35: Tender sum (before VAT) | F35: =F31+F32+F33+F34 -> 1980.72
B36: VAT | E36: 0.05 | F36: =F35*E36 -> 99.04
B37: Total | F37: =F35+F36 -> 2079.75
B39: i | C39: IN THIS WORKBOOK
B40: Takeoff | C40: Every measurement with its drawing, page, material, quantity, rate and amount.
B41: Bill of Quantities | C41: The priced bill, item by item under its work section, carried to a summary.
B42: BOQ_Matrix | C42: Each measured row against the material it uses; columns total each material.
B43: Materials | C43: What to order: net quantity, waste, sheet / pack size, order quantity, price and purchase cost.
B44: Cost_Breakdown | C44: Material, labour and equipment rates × quantity, with VAT and a check against the Takeoff.
B45: Change log | C45: Who changed which quantity, rate or setting, and when.
A48: All quantities subject to field verification. Amber cells are inputs: rates still to price, percentages you can change.

Sheet Takeoff
B2: D01 · MEASURED QUANTITIES
B3: RAK Doors · Ras Al Khaimah · Rev B · 2026-10-13
B5: ★ One line per measurement, grouped as in Foldrule. Quantities include any timesing (see Notes). Rate = the row's own rate, else its material's. Amounts are live formulas.
B7: Item | C7: Description | D7: Drawing | E7: Page | F7: Measured as | G7: Material | H7: Quantity | I7: Unit | J7: Rate | K7: Amount | L7: Notes
B8: 1 | C8: Door Leaf | D8: ARAK-P1R1-INB-SD-ID-RES-ZZZ-3320277-02.pdf | K8: =SUM(K9:K10) | M8: 1
B9: 1.1 | C9: Door Leaf | D9: ARAK-P1R1-INB-SD-ID-RES-ZZZ-3320277-02.pdf | E9: 1 | F9: Area | G9: FR60mins Doorcore | H9: 2.047494 | I9: m² | J9: 100 | K9: =H9*J9
B10: 1.2 | C10: Door Leaf | D10: ARAK-P1R1-INB-SD-ID-RES-ZZZ-3320277-02.pdf | E10: 1 | F10: Area | G10: Wrapping Veneer WD002 | H10: 4.0849 | I10: m² | J10: 30 | K10: =H10*J10 | L10: 2.0424 sq m × 2
B11: 2 | C11: DOOR Architrave | D11: ARAK-P1R1-INB-SD-ID-RES-ZZZ-3320277-02.pdf | K11: =SUM(K12:K15) | M11: 1
B12: 2.1 | C12: DOOR Architrave | D12: ARAK-P1R1-INB-SD-ID-RES-ZZZ-3320277-02.pdf | E12: 1 | F12: Area | G12: 12mmThk plain MDF | H12: 2.0533387 | I12: m² | J12: 41.354167 | K12: =H12*J12
B13: 2.2 | C13: DOOR Architrave 2 | D13: ARAK-P1R1-INB-SD-ID-RES-ZZZ-3320277-02.pdf | E13: 1 | F13: Area | G13: Wrapping Veneer WD002 | H13: 2.0523932 | I13: m² | J13: 30 | K13: =H13*J13
B14: 2.3 | C14: DOOR Architrave 3 | D14: ARAK-P1R1-INB-SD-ID-RES-ZZZ-3320277-02.pdf | E14: 1 | F14: Area | G14: Timber | H14: 0.31648306 | I14: m² | J14: 140 | K14: =H14*J14
B15: 2.4 | C15: DOOR Architrave 4 | D15: ARAK-P1R1-INB-SD-ID-RES-ZZZ-3320277-02.pdf | E15: 1 | F15: Area | G15: Wrapping Veneer WD002 | H15: 0.33412734 | I15: m² | J15: 30 | K15: =H15*J15
B16: 3 | C16: DOOR Architrave | D16: ARAK-P1R1-INB-SD-ID-RES-ZZZ-3320361-01.pdf | K16: 0 | M16: 1
B17: 4 | C17: Door Frame | D17: ARAK-P1R1-INB-SD-ID-RES-ZZZ-3320361-01.pdf | K17: =SUM(K18:K18) | M17: 1
B18: 4.1 | C18: Door Frame | D18: ARAK-P1R1-INB-SD-ID-RES-ZZZ-3320361-01.pdf | E18: 1 | F18: Area | G18: Solid Wood | H18: 0.0083957392 | I18: m² | J18: 0 | K18: =H18*J18
B19: 5 | C19: Door Frame | D19: ARAK-P1R1-INB-SD-ID-RES-ZZZ-3320277-02.pdf | K19: =SUM(K20:K22) | M19: 1
B20: 5.1 | C20: Door Frame 1 | D20: ARAK-P1R1-INB-SD-ID-RES-ZZZ-3320277-02.pdf | E20: 1 | F20: Length | G20: Solid Wood | H20: 5.3324 | I20: m | J20: 57 | K20: =H20*J20
B21: 5.2 | C21: Door Frame 2 | D21: ARAK-P1R1-INB-SD-ID-RES-ZZZ-3320277-02.pdf | E21: 1 | F21: Length | G21: Wrapping Veneer WD002 | H21: 2.1992 | I21: m | J21: 30 | K21: =H21*J21
B22: 5.3 | C22: Door Frame 3 | D22: ARAK-P1R1-INB-SD-ID-RES-ZZZ-3320277-02.pdf | E22: 1 | F22: Length | G22: Wrapping Veneer WD002 | H22: 0.2666 | I22: m | J22: 30 | K22: =H22*J22
B23: M1 | C23: Ironmongery set (hinges, lock, closer) | D23: ARAK-P1R1-INB-SD-ID-RES-ZZZ-3320277-02.pdf | F23: Typed in | G23: — | H23: 1 | I23: nr | J23: 650 | K23: =H23*J23 | M23: 1
J25: Subtotal | K25: =SUMIF(M8:M23,1,K8:K23)
J26: VAT 5% | K26: =K25*5/100
J27: Total | K27: =K25+K26
A30: Prepared with Foldrule · 2026-10-14 · Amber rates are still to be priced.

Sheet Bill of Quantities
B2: BILL OF QUANTITIES
B3: RAK Doors · Ras Al Khaimah · Rev B · 2026-10-13
B5: ★ Items follow the work sections of the Principles of Measurement (International). Groups whose rows share a unit are billed as one item. Quantities as billed, to two decimals; the measured detail is on the Takeoff sheet.
B7: Item | C7: Description | D7: Quantity | E7: Unit | F7: Rate | G7: Amount
B8: H | C8: DOORS AND WINDOWS | F8: 5 items
B9: A | C9: Door Leaf | D9: 6.13 | E9: m² | F9: 53.3717 | G9: =D9*F9
B10: B | C10: DOOR Architrave | D10: 4.76 | E10: m² | F10: 42.221 | G10: =D10*F10
B11: C | C11: Door Frame | D11: 0.01 | E11: m² | F11: 0 | G11: =D11*F11
B12: D | C12: Door Frame | D12: 7.8 | E12: m | F12: 48.4626 | G12: =D12*F12
B13: E | C13: Ironmongery set (hinges, lock, closer) | D13: 1 | E13: nr | F13: 650 | G13: =D13*F13
E14: Carried to summary | G14: =SUM(G9:G13)
B16: Σ | C16: SUMMARY
B17: H | C17: Doors and windows | G17: =G14
E18: Subtotal | G18: =SUM(G17:G17)
E19: VAT 5% | G19: =G18*5/100
E20: Total | G20: =G18+G19
A23: All quantities subject to field verification. Amber rates are still to be priced.

Sheet BOQ_Matrix
B2: BOQ MATRIX · D01 · QUANTITIES BY MATERIAL
B3: RAK Doors · Ras Al Khaimah · Rev B · 2026-10-13
B5: ★ Each row's quantity is carried into its material's column. "Times" multiplies a row (blank = 1). Section totals add up each column. Materials and Cost_Breakdown take their quantities from the PROJECT TOTALS row.
B7: S.No | C7: Description | D7: Unit | E7: Times | F7: Measured | G7: Total QTY | H7: FR60mins Doorcore (m²) | I7: Wrapping Veneer WD002 (m²) | J7: 12mmThk plain MDF (m²) | K7: Timber (m²) | L7: Solid Wood (m²) | M7: Solid Wood (m) | N7: Wrapping Veneer WD002 (m) | O7: Remarks
B8: H | C8: DOORS AND WINDOWS | N8: 5 groups
C9: Door Leaf | D9: — | E9: — | F9: — | G9: — | O9: ARAK-P1R1-INB-SD-ID-RES-ZZZ-3320277-02.pdf
B10: 1.1 | C10: Door Leaf | D10: m² | F10: 2.047494 | G10: =F10*IF(E10<>"",E10,1) | H10: =G10
B11: 1.2 | C11: Door Leaf | D11: m² | F11: 4.0849 | G11: =F11*IF(E11<>"",E11,1) | I11: =G11 | O11: 2.0424 sq m × 2
C12: DOOR Architrave | D12: — | E12: — | F12: — | G12: — | O12: ARAK-P1R1-INB-SD-ID-RES-ZZZ-3320277-02.pdf
B13: 2.1 | C13: DOOR Architrave | D13: m² | F13: 2.0533387 | G13: =F13*IF(E13<>"",E13,1) | J13: =G13
B14: 2.2 | C14: DOOR Architrave 2 | D14: m² | F14: 2.0523932 | G14: =F14*IF(E14<>"",E14,1) | I14: =G14
B15: 2.3 | C15: DOOR Architrave 3 | D15: m² | F15: 0.31648306 | G15: =F15*IF(E15<>"",E15,1) | K15: =G15
B16: 2.4 | C16: DOOR Architrave 4 | D16: m² | F16: 0.33412734 | G16: =F16*IF(E16<>"",E16,1) | I16: =G16
C17: Door Frame | D17: — | E17: — | F17: — | G17: — | O17: ARAK-P1R1-INB-SD-ID-RES-ZZZ-3320361-01.pdf
B18: 4.1 | C18: Door Frame | D18: m² | F18: 0.0083957392 | G18: =F18*IF(E18<>"",E18,1) | L18: =G18
C19: Door Frame | D19: — | E19: — | F19: — | G19: — | O19: ARAK-P1R1-INB-SD-ID-RES-ZZZ-3320277-02.pdf
B20: 5.1 | C20: Door Frame 1 | D20: m | F20: 5.3324 | G20: =F20*IF(E20<>"",E20,1) | M20: =G20
B21: 5.2 | C21: Door Frame 2 | D21: m | F21: 2.1992 | G21: =F21*IF(E21<>"",E21,1) | N21: =G21 | O21: Measured in m; Wrapping Veneer WD002 is sold per m²
B22: 5.3 | C22: Door Frame 3 | D22: m | F22: 0.2666 | G22: =F22*IF(E22<>"",E22,1) | N22: =G22 | O22: Measured in m; Wrapping Veneer WD002 is sold per m²
C23: Other items | D23: — | E23: — | F23: — | G23: —
B24: M1 | C24: Ironmongery set (hinges, lock, closer) | D24: nr | F24: 1 | G24: =F24*IF(E24<>"",E24,1)
B25: Section H total | H25: =SUM(H9:H24) | I25: =SUM(I9:I24) | J25: =SUM(J9:J24) | K25: =SUM(K9:K24) | L25: =SUM(L9:L24) | M25: =SUM(M9:M24) | N25: =SUM(N9:N24)
A29: PROJECT TOTALS — All sections
B30: Total QTY | H30: =H25 | I30: =I25 | J30: =J25 | K30: =K25 | L30: =L25 | M30: =M25 | N30: =N25
H31: FR60mins Doorcore (m²) | I31: Wrapping Veneer WD002 (m²) | J31: 12mmThk plain MDF (m²) | K31: Timber (m²) | L31: Solid Wood (m²) | M31: Solid Wood (m) | N31: Wrapping Veneer WD002 (m)

Sheet Materials
B2: MATERIALS LIST · WHAT TO ORDER
B3: RAK Doors · Ras Al Khaimah · Rev B · 2026-10-13
B5: ★ Net quantities are live from BOQ_Matrix (project totals). Gross = net + waste. Enter a sheet or pack size (amber) and the order rounds up to whole sheets / packs; leave it blank to order the gross quantity. Price each is the material price per "buy by" unit — material only, no labour or equipment.
B7: # | C7: Code | D7: Material | E7: Unit | F7: Net quantity | G7: Waste | H7: Gross quantity | I7: Sheet / pack size | J7: Buy by | K7: Order quantity | L7: Price each | M7: Purchase cost | N7: Supplier | O7: Remarks
B8: 1 | C8: 06 00 01 | D8: FR60mins Doorcore | E8: m² | F8: ='BOQ_Matrix'!H30 -> 2.047494 | G8: 0 | H8: =F8*(1+G8) | J8: m² | K8: =IF(I8="",ROUND(H8,2),CEILING(H8/I8,1)) | L8: 85 | M8: =K8*L8
B9: 2 | C9: 06 00 00 | D9: Wrapping Veneer WD002 | E9: m² | F9: ='BOQ_Matrix'!I30 -> 6.4714205 | G9: 0.1 | H9: =F9*(1+G9) | J9: m² | K9: =IF(I9="",ROUND(H9,2),CEILING(H9/I9,1)) | L9: 22 | M9: =K9*L9
B10: 3 | C10: 06 00 00 | D10: 12mmThk plain MDF | E10: m² | F10: ='BOQ_Matrix'!J30 -> 2.0533387 | G10: 0.05 | H10: =F10*(1+G10) | I10: 2.88 | J10: sheet | K10: =IF(I10="",ROUND(H10,2),CEILING(H10/I10,1)) | L10: 86 | M10: =K10*L10 | O10: One sheet covers 2.88 m²
B11: 4 | C11: 06 00 00 | D11: Timber | E11: m² | F11: ='BOQ_Matrix'!K30 -> 0.31648306 | G11: 0 | H11: =F11*(1+G11) | J11: m² | K11: =IF(I11="",ROUND(H11,2),CEILING(H11/I11,1)) | L11: 120 | M11: =K11*L11
B12: 5 | C12: 06 00 00 | D12: Solid Wood | E12: m² | F12: ='BOQ_Matrix'!L30 -> 0.0083957392 | G12: 0 | H12: =F12*(1+G12) | J12: m² | K12: =IF(I12="",ROUND(H12,2),CEILING(H12/I12,1)) | M12: =K12*L12
B13: 6 | C13: 06 00 00 | D13: Solid Wood | E13: m | F13: ='BOQ_Matrix'!M30 -> 5.3324 | G13: 0 | H13: =F13*(1+G13) | J13: m | K13: =IF(I13="",ROUND(H13,2),CEILING(H13/I13,1)) | L13: 45 | M13: =K13*L13
B14: 7 | C14: 06 00 00 | D14: Wrapping Veneer WD002 | E14: m | F14: ='BOQ_Matrix'!N30 -> 2.4658 | G14: 0.1 | H14: =F14*(1+G14) | J14: m | K14: =IF(I14="",ROUND(H14,2),CEILING(H14/I14,1)) | L14: — | M14: — | O14: Measured in m but sold per m²: convert (e.g. length × girth) before ordering
I15: Materials to buy (excl. VAT) | M15: =SUM(M8:M14)
A18: Order quantities include waste and round up to whole sheets / packs where a size is given. Check against site conditions before ordering.

Sheet Cost_Breakdown
B2: COST BREAKDOWN · QUANTITIES × UNIT RATES
B3: RAK Doors · Ras Al Khaimah · Rev B · 2026-10-13 · AED · VAT 5%
B5: ★ Quantities are live from the Materials sheet. Unit rate = material (incl. waste) + labour + equipment; where rows carry their own rate, the average rate of those rows is used so this sheet agrees with the Takeoff. Green = rate from data · Amber = still to be priced.
B7: # | C7: Code | D7: Description | E7: Unit | F7: Quantity | G7: Material rate | H7: Labour rate | I7: Equipment rate | J7: Unit rate | K7: Amount | L7: Notes
B8: M | C8: MATERIALS | K8: 7 lines
B9: 1 | C9: 06 00 01 | D9: FR60mins Doorcore | E9: m² | F9: ='Materials'!F8 -> 2.047494 | G9: 85 | H9: 15 | J9: =G9+H9+I9 -> 100 | K9: =F9*J9
B10: 2 | C10: 06 00 00 | D10: Wrapping Veneer WD002 (m²) | E10: m² | F10: ='Materials'!F9 -> 6.4714205 | G10: 24.2 | H10: 8 | J10: 30 | K10: =F10*J10 | L10: Stored rate (build-up 32.2)
B11: 3 | C11: 06 00 00 | D11: 12mmThk plain MDF | E11: m² | F11: ='Materials'!F10 -> 2.0533387 | G11: 31.3542 | H11: 10 | J11: =G11+H11+I11 -> 41.3542 | K11: =F11*J11
B12: 4 | C12: 06 00 00 | D12: Timber | E12: m² | F12: ='Materials'!F11 -> 0.31648306 | G12: 120 | H12: 20 | J12: =G12+H12+I12 -> 140 | K12: =F12*J12
B13: 5 | C13: 06 00 00 | D13: Solid Wood (m²) | E13: m² | F13: ='Materials'!F12 -> 0.0083957392 | K13: =F13*J13 | L13: Not priced yet
B14: 6 | C14: 06 00 00 | D14: Solid Wood (m) | E14: m | F14: ='Materials'!F13 -> 5.3324 | G14: 45 | H14: 12 | J14: =G14+H14+I14 -> 57 | K14: =F14*J14
B15: 7 | C15: 06 00 00 | D15: Wrapping Veneer WD002 (m) | E15: m | F15: ='Materials'!F14 -> 2.4658 | G15: 24.2 | H15: 8 | J15: 30 | K15: =F15*J15 | L15: Measured in m, priced per m² · Stored rate (build-up 32.2)
B17: O | C17: ITEMS WITHOUT A MATERIAL | K17: 1 item
B18: M1 | D18: Ironmongery set (hinges, lock, closer) | E18: nr | F18: ='Takeoff'!H23 -> 1 | J18: 650 | K18: =F18*J18 | L18: Takeoff item M1
H20: Subtotal (excl. VAT) | K20: =K9+K10+K11+K12+K13+K14+K15+K18
H21: VAT (5%) | K21: =K20*5/100
H22: GRAND TOTAL (incl. VAT) | K22: =K20+K21
H24: Check: Takeoff total before VAT | K24: ='Takeoff'!K25
H25: Difference (should be 0) | K25: =ROUND(K20-K24,2)
A28: Rates to be confirmed by the tendering contractor. All quantities are subject to field verification.

Sheet Change log
B2: CHANGE LOG · WHO CHANGED WHAT
B3: RAK Doors · Ras Al Khaimah · Rev B · 2026-10-13
B5: ★ Every change to a quantity, rate, material, price or estimate setting, newest first.
B7: When | C7: Who | D7: What | E7: Item | F7: From | G7: To
B8: 46309.211 | C8: munsif | D8: Material | E8: Door Frame 3 | F8: Solid Wood | G8: Wrapping Veneer WD002
B9: 46309.211 | C9: munsif | D9: Added | E9: Door Frame 3 | G9: 0.267 m
B10: 46309.198 | C10: munsif | D10: Quantity | E10: Door Leaf | F10: 2.047 sq m | G10: 2.042 sq m
B11: 46308.445 | C11: munsif | D11: Setting | E11: VAT | F11: not set | G11: 5%
A14: Times are in the exporting computer's clock.
